Workbook

Sheet Sheet1
A1: Date | B1: Text | C1: Text Normalization | D1: Brand | E1: Sentimen | F1: Encoded_Label | G1: Validasi Sentimen | H1: Validasi Aspect
A2: 04/2024 | B2: Tuku , fore, ksk , point coffe | C2: tuku fore ksk point coffee coffe | D2: fore | E2: positive | F2: 2 | G2: =LOWER(Sheet2!D2) -> neutral | H2: None
A3: 05/2024 | B3: Tuku, XXI (maaf bgt soalnya emg kopi pandannya enak betul), dan Fore | C3: tuku xxi maaf banget memang kopi pandannya enak fore | D3: fore | E3: negative | F3: 0 | G3: =LOWER(Sheet2!D3) -> positive | H3: None
A4: 11/2024 | B4: Aku juga suka hojichanya matchamu. Dulu di fore ada menu hojicha latte enak bgt, tp sayang skrg udah ga ada | C4: suka hojichanya matchamu fore menu hojicha latte enak banget sayang | D4: fore | E4: positive | F4: 2 | G4: =LOWER(Sheet2!D4) -> negative | H4: Produk
A5: 08/2024 | B5: Fore, buttercream latte Kozi, kosangsu foam charcoal Buih, es kopi buih | C5: fore buttercream latte kozi kosangsu foam charcoal buih es kopi buih | D5: fore | E5: positive | F5: 2 | G5: =LOWER(Sheet2!D5) -> neutral | H5: None
A6: 04/2024 | B6: 1. Tuku 2. Fore 3. Versi belasan ribu KSK Family mart | C6: 1 tuku 2 fore 3 versi belasan ksk family mart | D6: fore | E6: neutral | F6: 1 | G6: =LOWER(Sheet2!D6) -> neutral | H6: None
A7: 02/2024 | B7: Mau tau dong fess jagoan kalian disetiap outlet minuman ini apa aja - Point coffee: cookies and cream - Tomoro: carramel machiato - Fore: buttercream tirramisu latte - Haus: Lemon tea, choco hazelnut cheese - Es.Teh Indonesia: Teh susu nusantara | C7: fess jagoan disetiap outlet minuman point coffee coffee cookies and cream tomoro carramel machiato fore buttercream tirramisu latte haus lemon tea choco hazelnut cheese esteh indonesia kakak perempuan susu nusantara | D7: fore | E7: positive | F7: 2 | G7: =LOWER(Sheet2!D7) -> positive | H7: None
A8: 04/2024 | B8: Tuku, fore, kenangan, & point cafe (tapi lebih suka yg kopi sakunya ) | C8: tuku fore kenangan point coffee cafe suka kopi sakunya | D8: fore | E8: positive | F8: 2 | G8: =LOWER(Sheet2!D8) -> positive | H8: Produk
A9: 06/2024 | B9: tomoro, fore, point, kopken itu aku cocok sama rasanya tp yg friendly ke lambungku cuma kopken plis | C9: tomoro fore point coffee kopi kenangan cocok friendly lambungku kopi kenangan plis | D9: fore | E9: positive | F9: 2 | G9: =LOWER(Sheet2!D9) -> positive | H9: Produk
A10: 01/2024 | B10: tuku sama fore best so far sih | C10: tuku fore best so far sih | D10: fore | E10: positive | F10: 2 | G10: =LOWER(Sheet2!D10) -> positive | H10: Produk
A11: 04/2024 | B11: Tuku &amp; fore | C11: tuku amp fore | D11: fore | E11: negative | F11: 0 | G11: =LOWER(Sheet2!D11) -> negative | H11: None
A12: 06/2024 | B12: aiko nuju & aren latte fore BEST +1 lagi palm sugar latte point coffee tapi ga ada fotonya | C12: aiko nuju aren latte fore best 1 palm gula latte point coffee coffee fotonya | D12: fore | E12: positive | F12: 2 | G12: =LOWER(Sheet2!D12) -> positive | H12: Produk
A13: 05/2024 | B13: Fore enk gk berat rasanya Kalau kenangan rasa kopi lbh berasa dan agak berat kyk creamy atau gimana gitu jelasinnya ya | C13: fore enk gk kenangan kopi lbh berasa agak creamy jelasinnya iya | D13: fore | E13: positive | F13: 2 | G13: =LOWER(Sheet2!D13) -> positive | H13: Produk
... A1822: 04/2024 | B1822: sejauh ini point dan fore aman di lidah, lambung dan dompet | C1822: point coffee fore aman lidah lambung dompet | D1822: fore | E1822: neutral | F1822: 1 | G1822: =LOWER(Sheet2!D1822) -> positive | H1822: Produk

Sheet Sheet2
A1: Positive | B1: Produk
A2: Neutral | B2: Layanan | D2: Neutral
A3: Negative | B3: None | D3: Positive
D4: Negative
D5: Neutral
D6: Neutral
D7: Positive
D8: Positive
D9: positive
D10: positive
D11: negative
D12: positive
D13: positive
D14: neutral
D15: positive
... D1822: Positive
